Metadata-Version: 2.1
Name: django4-cron
Version: 0.5.1
Summary: Running python crons in a Django project. Updated to work with Django 4.0 by Rehmat Alam.
Home-page: http://github.com/rehmatworks/django-cron
Author: Sumit Chachra
Author-email: chachra@tivix.com
License: UNKNOWN
Keywords: django django 4 cron
Platform: UNKNOWN
Classifier: Framework :: Django
Classifier: Intended Audience :: Developers
Classifier: Intended Audience :: System Administrators
Classifier: Operating System :: OS Independent
Classifier: Topic :: Software Development
License-File: LICENSE
License-File: AUTHORS
